{
    "unpublished": {
        "author": "authorAffiliations:",
    },
    "book": {},
    "inbook": {},
    "conference": {},
    "proceedings": {},
    "misc": {},
    "techreport": {},
    "phdthesis": {
        "author": "authorAffiliations:meta:author:name",
        "title": "title",
        "school": "authorAffiliations:meta:organization:name",
        "address": "authorAffiliations:meta:organization:location",
        "year": "publications:publicationDate.year",
        "month": "publications:publicationDate.month"
    },
    "all": {
        "categories": "subjectCategories",
        "abstract": "abstract",
        "keywords": "keywords",
    }
}